FrameworkAPI/__init__.py
FrameworkAPI/version.py
FrameworkAPI/core/FrameworkAPI.py
FrameworkAPI/core/__init__.py
FrameworkAPI/example/__init__.py
FrameworkAPI/example/example.py
frameworkapi-0.0.6.4.dist-info/METADATA
frameworkapi-0.0.6.4.dist-info/WHEEL
frameworkapi-0.0.6.4.dist-info/top_level.txt
frameworkapi-0.0.6.4.dist-info/RECORD
