Metadata-Version: 2.1
Name: frameworkapi
Version: 0.0.6.4
Summary: Python module to easily run scripts in modular frameworks Written by pedrohenriquecoimbra
Home-page: https://github.com/pedrohenriquecoimbra/FrameworkAPI
Author: Pedro Henrique Coimbra
Author-email: pedro-henrique.herig-coimbra@inrae.fr
License: MIT
Keywords: modular,lazy,callable
Platform: any
Classifier: Development Status :: 4 - Beta
Classifier: Environment :: Other Environment
Classifier: Framework :: Jupyter
Classifier: Intended Audience :: Science/Research
Classifier: Programming Language :: Python
Classifier: Programming Language :: Python :: 3
Classifier: Programming Language :: Python :: 3.8
Classifier: Programming Language :: Python :: 3.9
Classifier: Programming Language :: Python :: 3.10
Classifier: Programming Language :: Python :: 3.11
Classifier: Programming Language :: Python :: 3.12
Classifier: Programming Language :: Python :: 3.13
Classifier: Programming Language :: Python :: 3.14
Classifier: Topic :: Other/Nonlisted Topic
Requires-Python: >=3.8
Requires-Dist: PyYAML
